evocov/__init__.py
evocov/fitting_methods/__init__.py
evocov/fitting_methods/evocov.py
evocov/fitting_methods/genetic_programming.py
evocov/fitting_methods/go_with_the_first.py
evocov/fitting_methods/greedy.py
evocov/fitting_methods/kernel_fitting_method.py
evocov/fitting_methods/moecov.py
evocov/fitting_methods/random.py
evocov/gen_prog_tools/__init__.py
evocov/gen_prog_tools/creation.py
evocov/gen_prog_tools/crossover.py
evocov/gen_prog_tools/mutation.py
evocov/gen_prog_tools/primitive_set.py
evocov/gen_prog_tools/selection.py
evocov/kernel_functions/__init__.py
evocov/kernel_functions/gen_prog_kernel.py
evocov/metrics/__init__.py
evocov/metrics/meta_metric.py
evocov-0.1.0.dist-info/LICENSE.txt
evocov-0.1.0.dist-info/METADATA
evocov-0.1.0.dist-info/WHEEL
evocov-0.1.0.dist-info/top_level.txt
evocov-0.1.0.dist-info/RECORD
