Metadata-Version: 2.1
Name: evocov
Version: 0.1.0
Summary: GPlib extension to learn the kernel function.
Home-page: https://gitlab.com/ibaidev/evocov
Author: Ibai Roman
Author-email: ibaidev@protonmail.com
License: GPLv3
Keywords: Kernel Learning
Platform: UNKNOWN
Classifier: Development Status :: 4 - Beta
Classifier: Environment :: Console
Classifier: Intended Audience :: Developers
Classifier: Intended Audience :: Science/Research
Classifier: License :: OSI Approved :: GNU General Public License v3 (GPLv3)
Classifier: Operating System :: POSIX
Classifier: Programming Language :: Python
Classifier: Topic :: Scientific/Engineering :: Artificial Intelligence
License-File: LICENSE.txt
Requires-Dist: gplib
Requires-Dist: numpy
Requires-Dist: deap
